{
  "asset": {
    "version": "1.0"
  },
  "geometricError": 100,
  "root": {
    "refine": "ADD",
    "transform": [
      -0.9659258262890682,
      -0.25881904510252085,
      0,
      0,
      0.09695531991670876,
      -0.36184217999325163,
      0.9271838559409777,
      0,
      -0.2399728402291171,
      0.8955908321716735,
      0.37460659001467134,
      0,
      -1531296.6870677804,
      5714877.037598854,
      2374409.1492368816,
      1
    ],
    "boundingVolume": {
      "box": [
        0,
        0,
        10,
        1067.83855,
        0,
        0,
        0,
        547.58553,
        0,
        0,
        0,
        10
      ]
    },
    "geometricError": 100,
    "children": [
      {
        "geometricError": 100,
        "transform": [
          1,
          0,
          0,
          0,
          0,
          1,
          0,
          0,
          0,
          0,
          1,
          0,
          -545.80615,
          -44.94163,
          0,
          1
        ],
        "boundingVolume": {
          "box": [
            0,
            0,
            10,
            1067.83855,
            0,
            0,
            0,
            547.58553,
            0,
            0,
            0,
            10
          ]
        },
        "children": [
          {
            "boundingVolume": {
              "box": [
                -1073.3368835449219,
                427.36814880371094,
                0.0005000000237487257,
                540.3077697753906,
                0,
                0,
                0,
                75.27574157714844,
                0,
                0,
                0,
                0.0005000000237487257
              ]
            },
            "content": {
              "uri": "./middleware/output/b3dm/__0_001_.b3dm"
            },
            "geometricError": 0
          },
          {
            "boundingVolume": {
              "box": [
                112.9012451171875,
                -266.2635803222656,
                0.0005000000237487257,
                409.13116455078125,
                0,
                0,
                0,
                326.2635803222656,
                0,
                0,
                0,
                0.0005000000237487257
              ]
            },
            "content": {
              "uri": "./middleware/output/b3dm/__0_100_.b3dm"
            },
            "geometricError": 0
          },
          {
            "boundingVolume": {
              "box": [
                5.06719970703125,
                65.74549198150635,
                10,
                67.91168212890625,
                0,
                0,
                0,
                45.44138240814209,
                0,
                0,
                0,
                10
              ]
            },
            "content": {
              "uri": "./middleware/output/b3dm/__0_111_.b3dm"
            },
            "geometricError": 0
          },
          {
            "boundingVolume": {
              "box": [
                -180.29869079589844,
                70.16218566894531,
                6.25,
                240.29869079589844,
                0,
                0,
                0,
                220.1621856689453,
                0,
                0,
                0,
                6.25
              ]
            },
            "content": {
              "uri": "./middleware/output/b3dm/__0_101__1_000_.b3dm"
            },
            "geometricError": 0
          },
          {
            "boundingVolume": {
              "box": [
                -255.69379711151123,
                325.61544036865234,
                0.0005000000237487257,
                277.98308277130127,
                0,
                0,
                0,
                142.59357452392578,
                0,
                0,
                0,
                0.0005000000237487257
              ]
            },
            "content": {
              "uri": "./middleware/output/b3dm/__0_101__1_001_.b3dm"
            },
            "geometricError": 0
          },
          {
            "boundingVolume": {
              "box": [
                -64.12786054611206,
                67.22593688964844,
                6.25,
                58.255592823028564,
                0,
                0,
                0,
                43.9609375,
                0,
                0,
                0,
                6.25
              ]
            },
            "content": {
              "uri": "./middleware/output/b3dm/__0_101__1_010_.b3dm"
            },
            "geometricError": 0
          },
          {
            "boundingVolume": {
              "box": [
                152.89533233642578,
                28.482528686523438,
                6.25,
                283.42467498779297,
                0,
                0,
                0,
                160.74560546875,
                0,
                0,
                0,
                6.25
              ]
            },
            "content": {
              "uri": "./middleware/output/b3dm/__0_101__1_100_.b3dm"
            },
            "geometricError": 0
          },
          {
            "boundingVolume": {
              "box": [
                30.49670648574829,
                57.17347049713135,
                10,
                42.48217535018921,
                0,
                0,
                0,
                36.86936092376709,
                0,
                0,
                0,
                10
              ]
            },
            "content": {
              "uri": "./middleware/output/b3dm/__0_101__1_110_.b3dm"
            },
            "geometricError": 0
          }
        ]
      }
    ]
  }
}